pySOT/__init__.py
pySOT/utils.py
pySOT/auxiliary_problems/__init__.py
pySOT/auxiliary_problems/candidate_dycors.py
pySOT/auxiliary_problems/candidate_srbf.py
pySOT/auxiliary_problems/candidate_uniform.py
pySOT/auxiliary_problems/ei_ga.py
pySOT/auxiliary_problems/ei_merit.py
pySOT/auxiliary_problems/lcb_ga.py
pySOT/auxiliary_problems/lcb_merit.py
pySOT/controller/__init__.py
pySOT/controller/controller.py
pySOT/experimental_design/__init__.py
pySOT/experimental_design/experimental_design.py
pySOT/experimental_design/lhd.py
pySOT/experimental_design/slhd.py
pySOT/experimental_design/two_factorial.py
pySOT/optimization_problems/__init__.py
pySOT/optimization_problems/ackley.py
pySOT/optimization_problems/branin.py
pySOT/optimization_problems/exponential.py
pySOT/optimization_problems/goldstein_price.py
pySOT/optimization_problems/griewank.py
pySOT/optimization_problems/hartmann3.py
pySOT/optimization_problems/hartmann6.py
pySOT/optimization_problems/himmelblau.py
pySOT/optimization_problems/levy.py
pySOT/optimization_problems/michaelewicz.py
pySOT/optimization_problems/optimization_problem.py
pySOT/optimization_problems/perm.py
pySOT/optimization_problems/rastrigin.py
pySOT/optimization_problems/rosenbrock.py
pySOT/optimization_problems/schwefel.py
pySOT/optimization_problems/six_hump_camel.py
pySOT/optimization_problems/sphere.py
pySOT/optimization_problems/sum_of_squares.py
pySOT/optimization_problems/weierstrass.py
pySOT/optimization_problems/zakharov.py
pySOT/strategy/__init__.py
pySOT/strategy/dycors_strategy.py
pySOT/strategy/ei_strategy.py
pySOT/strategy/lcb_strategy.py
pySOT/strategy/random_strategy.py
pySOT/strategy/sop_strategy.py
pySOT/strategy/srbf_strategy.py
pySOT/strategy/surrogate_strategy.py
pySOT/surrogate/__init__.py
pySOT/surrogate/gp.py
pySOT/surrogate/mars.py
pySOT/surrogate/poly.py
pySOT/surrogate/rbf.py
pySOT/surrogate/surrogate.py
pySOT/surrogate/kernels/__init__.py
pySOT/surrogate/kernels/cubic_kernel.py
pySOT/surrogate/kernels/kernel.py
pySOT-0.3.3.dist-info/LICENSE.rst
pySOT-0.3.3.dist-info/METADATA
pySOT-0.3.3.dist-info/WHEEL
pySOT-0.3.3.dist-info/top_level.txt
pySOT-0.3.3.dist-info/RECORD
