Metadata-Version: 2.1
Name: pySOT
Version: 0.3.3
Summary: Surrogate Optimization Toolbox
Home-page: https://github.com/dme65/pySOT
Author: David Eriksson, David Bindel, Christine Shoemaker
Author-email: dme65@cornell.edu, bindel@cornell.edu, shoemaker@nus.edu.sg
License: LICENSE.rst
Platform: UNKNOWN
Classifier: Intended Audience :: Science/Research
Classifier: Programming Language :: Python
Classifier: Topic :: Scientific/Engineering
Classifier: Operating System :: Microsoft :: Windows
Classifier: Operating System :: POSIX
Classifier: Operating System :: Unix
Classifier: Operating System :: MacOS
Classifier: Programming Language :: Python :: 3.4
Classifier: Programming Language :: Python :: 3.5
Classifier: Programming Language :: Python :: 3.6
Classifier: Programming Language :: Python :: 3.7
Requires-Dist: scipy
Requires-Dist: pyDOE2
Requires-Dist: POAP (>=0.1.25)
Requires-Dist: pytest
Requires-Dist: dill
Requires-Dist: scikit-learn
